{
	"info": {
		"_postman_id": "3af9dfb6-8e34-433a-92b8-2fe92b6bdf38",
		"name": "PilotoAPI",
		"schema": "https://schema.getpostman.com/json/collection/v2.1.0/collection.json",
		"_exporter_id": "9732508"
	},
	"item": [
		{
			"name": "GetAllProducts",
			"request": {
				"method": "GET",
				"header": [],
				"url": {
					"raw": "localhost:8080/api/product/",
					"host": [
						"localhost"
					],
					"port": "8080",
					"path": [
						"api",
						"product",
						""
					]
				}
			},
			"response": []
		},
		{
			"name": "CreateProduct",
			"request": {
				"method": "POST",
				"header": [],
				"body": {
					"mode": "raw",
					"raw": "{\n    \"name\":\"T1\",\n    \"description\":\"Teste\",\n    \"price\": 100.00,\n    \"quantity\": 10\n}",
					"options": {
						"raw": {
							"language": "json"
						}
					}
				},
				"url": {
					"raw": "localhost:8080/api/product/",
					"host": [
						"localhost"
					],
					"port": "8080",
					"path": [
						"api",
						"product",
						""
					]
				}
			},
			"response": []
		},
		{
			"name": "UpdateProduct",
			"request": {
				"method": "PUT",
				"header": [],
				"body": {
					"mode": "raw",
					"raw": "{\n    \"id\": 1,\n    \"name\":\"Teste1\",\n    \"description\":\"Teste\",\n    \"price\": 100.00,\n    \"quantity\": 10\n}",
					"options": {
						"raw": {
							"language": "json"
						}
					}
				},
				"url": {
					"raw": "localhost:8080/api/product/1",
					"host": [
						"localhost"
					],
					"port": "8080",
					"path": [
						"api",
						"product",
						"1"
					]
				}
			},
			"response": []
		},
		{
			"name": "DeleteProduct",
			"request": {
				"method": "DELETE",
				"header": [],
				"url": {
					"raw": "localhost:8080/api/product/1",
					"host": [
						"localhost"
					],
					"port": "8080",
					"path": [
						"api",
						"product",
						"1"
					]
				}
			},
			"response": []
		},
		{
			"name": "GetProduct",
			"request": {
				"method": "GET",
				"header": [],
				"url": {
					"raw": "localhost:8080/api/product/1",
					"host": [
						"localhost"
					],
					"port": "8080",
					"path": [
						"api",
						"product",
						"1"
					]
				}
			},
			"response": []
		}
	]
}